ibbycounts/__init__.py
ibbycounts/ibbycounts.py
ibbycounts/plotting.py
ibbycounts-0.1.0.dist-info/LICENSE
ibbycounts-0.1.0.dist-info/METADATA
ibbycounts-0.1.0.dist-info/WHEEL
ibbycounts-0.1.0.dist-info/RECORD
