Metadata-Version: 2.1
Name: ibbycounts
Version: 0.1.0
Summary: A package for doing great things!
License: MIT
Author: Ibrahim Saidi
Requires-Python: >=3.12
Classifier: License :: OSI Approved :: MIT License
Classifier: Programming Language :: Python :: 3
Requires-Dist: matplotlib (>=3.8.2)
